spectralcluster/__init__.py
spectralcluster/autotune.py
spectralcluster/configs.py
spectralcluster/constraint.py
spectralcluster/custom_distance_kmeans.py
spectralcluster/fallback_clusterer.py
spectralcluster/laplacian.py
spectralcluster/multi_stage_clusterer.py
spectralcluster/naive_clusterer.py
spectralcluster/refinement.py
spectralcluster/spectral_clusterer.py
spectralcluster/utils.py
spectralcluster-0.2.22.dist-info/LICENSE
spectralcluster-0.2.22.dist-info/METADATA
spectralcluster-0.2.22.dist-info/WHEEL
spectralcluster-0.2.22.dist-info/top_level.txt
spectralcluster-0.2.22.dist-info/RECORD
