Metadata-Version: 2.1
Name: spectralcluster
Version: 0.2.22
Summary: Spectral Clustering
Home-page: https://github.com/wq2012/SpectralCluster
Author: Quan Wang
Author-email: quanw@google.com
Classifier: Programming Language :: Python :: 3
Classifier: License :: OSI Approved :: Apache Software License
Classifier: Operating System :: OS Independent
License-File: LICENSE
Requires-Dist: numpy
Requires-Dist: scipy
Requires-Dist: scikit-learn
